burp_frame/__init__.py
burp_frame/bypass_ssl_manager.py
burp_frame/cert_manager.py
burp_frame/cli.py
burp_frame/config.py
burp_frame/device_manager.py
burp_frame/frida_manager.py
burp_frame/logger.py
burp_frame/proxy_manager.py
burp_frame/requirements.txt
burp_frame/universal_bypass_manager.py
burp_frame/utils.py
burp_frame/modules/__init__.py
burp_frame/modules/frida_cert_repin_bypass.py
burp_frame/modules/universal_bypass_manager.py
burp_frame-1.0.0.dist-info/licenses/LICENSE
burp_frame-1.0.0.dist-info/METADATA
burp_frame-1.0.0.dist-info/WHEEL
burp_frame-1.0.0.dist-info/entry_points.txt
burp_frame-1.0.0.dist-info/top_level.txt
burp_frame-1.0.0.dist-info/RECORD
