Metadata-Version: 2.4
Name: burp-frame
Version: 1.0.0
Summary: A unified Android penetration testing framework with certificate installation, proxy configuration, Frida instrumentation, and universal bypasses.
Author-email: Gashaw Kidanu <kidanugashaw@gmail.com>
License: MIT License
Project-URL: Homepage, https://github.com/Gashaw512/burp-frame
Project-URL: Bug Tracker, https://github.com/Gashaw512/burp-frame/issues
Keywords: android,burpsuite,certificate,installer,root,magisk,interception,security,frida,ssl-pinning,bypass,universal-bypass,mobile-security,pentesting
Classifier: Programming Language :: Python :: 3
Classifier: License :: OSI Approved :: MIT License
Classifier: Operating System :: OS Independent
Classifier: Development Status :: 4 - Beta
Classifier: Intended Audience :: Developers
Classifier: Intended Audience :: Science/Research
Classifier: Intended Audience :: System Administrators
Classifier: Topic :: Security
Classifier: Topic :: Software Development :: Libraries :: Python Modules
Classifier: Topic :: Utilities
Requires-Python: >=3.7
License-File: LICENSE
Requires-Dist: requests
Requires-Dist: colorama
Requires-Dist: frida
Dynamic: license-file
